maintenance_mode/__init__.py
maintenance_mode/backends.py
maintenance_mode/context_processors.py
maintenance_mode/core.py
maintenance_mode/decorators.py
maintenance_mode/http.py
maintenance_mode/io.py
maintenance_mode/logging.py
maintenance_mode/metadata.py
maintenance_mode/middleware.py
maintenance_mode/settings.py
maintenance_mode/urls.py
maintenance_mode/utils.py
maintenance_mode/views.py
maintenance_mode/management/__init__.py
maintenance_mode/management/commands/__init__.py
maintenance_mode/management/commands/maintenance_mode.py
maintenance_mode/templates/503.html
django_maintenance_mode-0.21.1.dist-info/LICENSE.txt
django_maintenance_mode-0.21.1.dist-info/METADATA
django_maintenance_mode-0.21.1.dist-info/WHEEL
django_maintenance_mode-0.21.1.dist-info/top_level.txt
django_maintenance_mode-0.21.1.dist-info/RECORD
