Metadata-Version: 2.1
Name: django-maintenance-mode
Version: 0.21.1
Summary: shows a 503 error page when maintenance-mode is on.
Author-email: Fabio Caccamo <fabio.caccamo@gmail.com>
Maintainer-email: Fabio Caccamo <fabio.caccamo@gmail.com>
Project-URL: Homepage, https://github.com/fabiocaccamo/django-maintenance-mode
Project-URL: Download, https://github.com/fabiocaccamo/django-maintenance-mode/releases
Project-URL: Documentation, https://github.com/fabiocaccamo/django-maintenance-mode#readme
Project-URL: Issues, https://github.com/fabiocaccamo/django-maintenance-mode/issues
Project-URL: Funding, https://github.com/sponsors/fabiocaccamo/
Project-URL: Twitter, https://twitter.com/fabiocaccamo
Keywords: django,maintenance,mode,offline,under,503,service,temporarily,unavailable
Classifier: Development Status :: 5 - Production/Stable
Classifier: Environment :: Web Environment
Classifier: Framework :: Django
Classifier: Framework :: Django :: 3.0
Classifier: Framework :: Django :: 3.1
Classifier: Framework :: Django :: 3.2
Classifier: Framework :: Django :: 4.0
Classifier: Framework :: Django :: 4.1
Classifier: Framework :: Django :: 4.2
Classifier: Framework :: Django :: 5.0
Classifier: Intended Audience :: Developers
Classifier: License :: OSI Approved :: MIT License
Classifier: Natural Language :: English
Classifier: Operating System :: OS Independent
Classifier: Programming Language :: Python :: 3
Classifier: Programming Language :: Python :: 3.8
Classifier: Programming Language :: Python :: 3.9
Classifier: Programming Language :: Python :: 3.10
Classifier: Programming Language :: Python :: 3.11
Classifier: Programming Language :: Python :: 3.12
Classifier: Topic :: Software Development :: Build Tools
License-File: LICENSE.txt
Requires-Dist: python-fsutil<1.0.0,>=0.13.1
